django_model_validation/__init__.py
django_model_validation/apps.py
django_model_validation/cache_field.py
django_model_validation/migration_operations.py
django_model_validation/models.py
django_model_validation/required_fields.py
django_model_validation/utils.py
django_model_validation/validators.py
django_model_validation-0.1.dist-info/METADATA
django_model_validation-0.1.dist-info/WHEEL
django_model_validation-0.1.dist-info/RECORD
